beansp/__init__.py
beansp/analyse.py
beansp/beans.py
beansp/burstrain.py
beansp/get_data.py
beansp/mrprior.py
beansp/run_emcee.py
beansp/run_model.py
beansp/settle.py
beansp/data/1731_bursts_avg.txt
beansp/data/1808_bursts.txt
beansp/data/1808_example_burstsfromminbar.png
beansp/data/1808_gti.txt
beansp/data/1808_mock_bursts1.secret
beansp/data/1808_mock_bursts1.txt
beansp/data/1808_obs.txt
beansp/data/1826_bursts.txt
beansp/data/beans.ini
beansp/data/example_1808_pfluxfromminbar.png
beansp/data/mr_prior_fit.txt
beansp-2.25.0.dist-info/LICENSE
beansp-2.25.0.dist-info/METADATA
beansp-2.25.0.dist-info/WHEEL
beansp-2.25.0.dist-info/top_level.txt
beansp-2.25.0.dist-info/RECORD
