Metadata-Version: 2.1
Name: beansp
Version: 2.25.0
Summary: Bayesian Estimation of Accreting Neutron Stars parameters
Home-page: https://github.com/adellej/beans
Author: 
Author-email: adelle.goodwin@curtin.edu.au
License: MIT license
Keywords: beans
Classifier: Development Status :: 2 - Pre-Alpha
Classifier: Intended Audience :: Developers
Classifier: License :: OSI Approved :: MIT License
Classifier: Natural Language :: English
Classifier: Programming Language :: Python :: 3.6
Classifier: Programming Language :: Python :: 3.7
Classifier: Programming Language :: Python :: 3.8
Classifier: Programming Language :: Python :: 3.9
Classifier: Programming Language :: Python :: 3.10
Requires-Python: >=3.6.0
License-File: LICENSE
Requires-Dist: numpy >=1.16
Requires-Dist: matplotlib
Requires-Dist: emcee >=3.0
Requires-Dist: corner
Requires-Dist: astropy
Requires-Dist: scipy
Requires-Dist: tables
Requires-Dist: chainconsumer
Requires-Dist: h5py >=2.10.0
Requires-Dist: pySettle
